pokr/__init__.py
pokr/_version.py
pokr/py.typed
pokr/tasks.py
pokr/metrics/__init__.py
pokr/metrics/github.py
pokr/metrics/todoist.py
pokr/templates/scorecard.html
pokr-0.2.1.dist-info/METADATA
pokr-0.2.1.dist-info/WHEEL
pokr-0.2.1.dist-info/top_level.txt
pokr-0.2.1.dist-info/RECORD
