Metadata-Version: 2.1
Name: pokr
Version: 0.2.1
Summary: Framework for building product and personal scorecards.
Home-page: UNKNOWN
Author: Ross Fenning
Author-email: github@rossfenning.co.uk
License: UNKNOWN
Platform: UNKNOWN
Requires-Dist: aiohttp
Requires-Dist: quart
Requires-Dist: invoke
Requires-Dist: doctrine
Requires-Dist: beautifulsoup4
Requires-Dist: PyGithub
Requires-Dist: todoist-python
Requires-Dist: cachetools
Requires-Dist: livereload
Requires-Dist: google-api-python-client
Requires-Dist: google-auth-httplib2
Requires-Dist: google-auth-oauthlib
Requires-Dist: feedparser
Requires-Dist: pybraries
Requires-Dist: pytz
Requires-Dist: google-analytics-data
Provides-Extra: test
Requires-Dist: pytest ; extra == 'test'
Requires-Dist: pytest-pikachu ; extra == 'test'
Requires-Dist: pytest-mypy ; extra == 'test'
Requires-Dist: pytest-asyncio ; extra == 'test'
Requires-Dist: types-cachetools ; extra == 'test'
Requires-Dist: types-requests ; extra == 'test'
Requires-Dist: types-pytz ; extra == 'test'
Requires-Dist: types-beautifulsoup4 ; extra == 'test'
